README.rst
setup.cfg
setup.py
twistyRL/__init__.py
twistyRL/core.py
twistyRL/poketCube.py
twistyRL/rubiksCube.py
twistyRL.egg-info/PKG-INFO
twistyRL.egg-info/SOURCES.txt
twistyRL.egg-info/dependency_links.txt
twistyRL.egg-info/requires.txt
twistyRL.egg-info/top_level.txt