Metadata-Version: 1.1
Name: twistyRL
Version: 0.1.20
Summary: twisty cube game for ML
Home-page: https://github.com/python-study-ko/twistyRL
Author: wesky93
Author-email: wesky93@gmail.com
License: MIT License
Keywords: cube,rubiks,twistycube,ML,RL
Platform: UNKNOWN
Classifier: Development Status :: 3 - Alpha
Classifier: Intended Audience :: Developers
Classifier: Programming Language :: Python
Classifier: Programming Language :: Python :: 3
Classifier: License :: OSI Approved :: MIT License
